lpcdbeclient
