Metadata-Version: 1.1
Name: lpcdbeclient
Version: 0.5
Summary: Client for inferencing the LPC DBE
Home-page: https://github.com/tklijnsma/lpcdbeclient.git
Author: Thomas Klijnsma
Author-email: tklijnsm@gmail.com
License: BSD 3-Clause License
Download-URL: https://github.com/tklijnsma/lpcdbeclient/archive/v0_5.tar.gz
Platform: UNKNOWN
